give_up_the_func/__init__.py
give_up_the_func/core.py
give_up_the_func/util.py
give_up_the_func-0.1.0.dist-info/LICENSE
give_up_the_func-0.1.0.dist-info/METADATA
give_up_the_func-0.1.0.dist-info/WHEEL
give_up_the_func-0.1.0.dist-info/top_level.txt
give_up_the_func-0.1.0.dist-info/RECORD
