Metadata-Version: 2.1
Name: give_up_the_func
Version: 0.1.0
Summary: A helper library for using function calling on local LLMs.
Home-page: https://github.com/gravitymonkey/give_up_the_func
Author: gravitymonkey
Author-email: jason@gravitymonkey.com
Keywords: chatbot,functions,LLM,AI
Classifier: Development Status :: 3 - Alpha
Classifier: Intended Audience :: Developers
Classifier: License :: OSI Approved :: MIT License
Classifier: Programming Language :: Python :: 3
Classifier: Programming Language :: Python :: 3.7
Classifier: Programming Language :: Python :: 3.8
Classifier: Programming Language :: Python :: 3.9
Classifier: Programming Language :: Python :: 3.10
Classifier: Programming Language :: Python :: 3.11
Requires-Python: >=3.7
License-File: LICENSE
Requires-Dist: openai
Requires-Dist: typing
